{"sections":{"main":{"type":"main-cart","settings":{}},"2fbaf1e1-147d-4fbf-9bc4-d90e771d10dc":{"type":"featured-product-carousel","settings":{"subheading":"","heading":"You May Also Like","description":"Upgrade your wardrobe with fewer, better items for the greener environment","content_align":"ta-left","show_navigation":true,"product_list":[],"image_ratio":"2\/3","image_overlay_opacity":30,"badge_text":"","badge_color":"color-accent-1","badge_position":"p-badge--bottom-right","badge_shape":"badge--star"}}},"order":["main","2fbaf1e1-147d-4fbf-9bc4-d90e771d10dc"]}